{
    "data": {
      "selfServiceMoveAvailable": false,
      "bookingKey": null,
      "recordLocator": null,
      "currencyCode": "INR",
      "systemCode": null,
      "groupName": null,
      "locators": {
        "numericRecordLocator": null,
        "parentRecordLocator": null,
        "parentId": 0,
        "recordLocators": []
      },
      "info": {
        "status": 0,
        "paidStatus": 0,
        "priceStatus": 2,
        "profileStatus": 0,
        "bookingType": null,
        "channelType": 0,
        "bookedDate": "2022-07-01T12:16:20.84193Z",
        "createdDate": null,
        "expirationDate": null,
        "modifiedDate": null,
        "modifiedAgentId": 0,
        "createdAgentId": 0,
        "owningCarrierCode": null,
        "changeAllowed": true
      },
      "sales": {
        "created": {
          "agentCode": "QPCCJ5003C_01",
          "domainCode": "EXT",
          "locationCode": "EXT",
          "organizationCode": "QPCCJ5003C"
        },
        "source": {
          "isoCountryCode": null,
          "sourceSystemCode": null,
          "agentCode": "QPCCJ5003C_01",
          "domainCode": "EXT",
          "locationCode": "EXT",
          "organizationCode": "QPCCJ5003C"
        },
        "modified": null
      },
      "typeOfSale": {
        "residentCountry": "IN",
        "promotionCode": null,
        "fareTypes": []
      },
      "hold": null,
      "breakdown": {
        "balanceDue": 57465,
        "pointsBalanceDue": 0,
        "authorizedBalanceDue": 57465,
        "totalAmount": 57465,
        "totalPoints": 0,
        "totalToCollect": 57465,
        "totalPointsToCollect": 0,
        "totalCharged": 57465,
        "passengerTotals": {
          "services": null,
          "specialServices": null,
          "seats": null,
          "upgrades": null,
          "spoilage": null,
          "nameChanges": null,
          "convenience": null,
          "infant": null
        },
        "passengers": {
          "MCFBRFQ-": {
            "passengerKey": "MCFBRFQ-",
            "services": null,
            "specialServices": null,
            "seats": null,
            "upgrades": null,
            "spoilage": null,
            "nameChanges": null,
            "convenience": null,
            "infant": null
          },
          "MSFBRFQ-": {
            "passengerKey": "MSFBRFQ-",
            "services": null,
            "specialServices": null,
            "seats": null,
            "upgrades": null,
            "spoilage": null,
            "nameChanges": null,
            "convenience": null,
            "infant": null
          },
          "MiFDSEQ-": {
            "passengerKey": "MiFDSEQ-",
            "services": null,
            "specialServices": null,
            "seats": null,
            "upgrades": null,
            "spoilage": null,
            "nameChanges": null,
            "convenience": null,
            "infant": null
          }
        },
        "journeyTotals": {
          "totalAmount": 53250,
          "totalPoints": 0,
          "totalTax": 4215,
          "totalDiscount": 0
        },
        "journeys": {
          "UVB_IDYwMn4gfn5TWFJ_MTAvMTQvMjAyMiAxMDowMH5CTFJ_MTAvMTQvMjAyMiAxMzo1MH5ERUx _": {
            "journeyKey": "UVB_IDYwMn4gfn5TWFJ_MTAvMTQvMjAyMiAxMDowMH5CTFJ_MTAvMTQvMjAyMiAxMzo1MH5ERUx _",
            "totalAmount": 17750,
            "totalPoints": 0,
            "totalTax": 1405,
            "totalDiscount": 0
          }
        },
        "addOnTotals": {
          "car": null,
          "hotel": null,
          "activities": null
        }
      },
      "receivedBy": null,
      "contacts": {},
      "passengers": {
        "MCFBRFQ-": {
          "passengerKey": "MCFBRFQ-",
          "passengerAlternateKey": null,
          "customerNumber": null,
          "fees": [],
          "name": null,
          "passengerTypeCode": "ADT",
          "discountCode": null,
          "bags": [],
          "program": null,
          "infant": null,
          "info": {
            "nationality": null,
            "residentCountry": null,
            "gender": 1,
            "dateOfBirth": null,
            "familyNumber": null
          },
          "travelDocuments": [],
          "addresses": [],
          "weightCategory": 1,
          "emdCoupons": []
        },
        "MSFBRFQ-": {
          "passengerKey": "MSFBRFQ-",
          "passengerAlternateKey": null,
          "customerNumber": null,
          "fees": [],
          "name": null,
          "passengerTypeCode": "ADT",
          "discountCode": null,
          "bags": [],
          "program": null,
          "infant": null,
          "info": {
            "nationality": null,
            "residentCountry": null,
            "gender": 1,
            "dateOfBirth": null,
            "familyNumber": null
          },
          "travelDocuments": [],
          "addresses": [],
          "weightCategory": 1,
          "emdCoupons": []
        },
        "MiFDSEQ-": {
          "passengerKey": "MiFDSEQ-",
          "passengerAlternateKey": null,
          "customerNumber": null,
          "fees": [],
          "name": null,
          "passengerTypeCode": "CHD",
          "discountCode": null,
          "bags": [],
          "program": null,
          "infant": null,
          "info": {
            "nationality": null,
            "residentCountry": null,
            "gender": 1,
            "dateOfBirth": null,
            "familyNumber": null
          },
          "travelDocuments": [],
          "addresses": [],
          "weightCategory": 3,
          "emdCoupons": []
        }
      },
      "journeys": [
        {
          "flightType": 2,
          "stops": 1,
          "designator": {
            "destination": "BLR",
            "origin": "SXR",
            "arrival": "2022-10-14T13:50:00",
            "departure": "2022-10-14T10:00:00"
          },
          "move": {
            "maxMoveBackDays": 365,
            "maxMoveOutDays": 365
          },
          "segments": [
            {
              "isStandby": false,
              "isConfirming": true,
              "isConfirmingExternal": false,
              "isBlocked": false,
              "isHosted": true,
              "isChangeOfGauge": false,
              "designator": {
                "destination": "BLR",
                "origin": "SXR",
                "arrival": "2022-10-14T13:50:00",
                "departure": "2022-10-14T10:00:00"
              },
              "isSeatmapViewable": true,
              "fares": [
                {
                  "isGoverning": true,
                  "downgradeAvailable": false,
                  "carrierCode": "QP",
                  "fareKey": "MH5Cfn5RUH5CTzdSQklOWH4xMDAxfn4yfjF_TkJMUlNYUjAwMjAwMTB_WA--",
                  "classOfService": "B",
                  "classType": null,
                  "fareApplicationType": 0,
                  "fareClassOfService": "B",
                  "fareBasisCode": "BO7RBINX",
                  "fareSequence": 1,
                  "inboundOutBound": 0,
                  "fareStatus": 0,
                  "isAllotmentMarketFare": false,
                  "originalClassOfService": "B",
                  "ruleNumber": "1001",
                  "productClass": "EC",
                  "ruleTariff": null,
                  "travelClassCode": "Y",
                  "crossReferenceClassOfService": null,
                  "passengerFares": [
                    {
                      "serviceCharges": [
                        {
                          "amount": 17750,
                          "code": null,
                          "detail": null,
                          "type": 0,
                          "collectType": 0,
                          "currencyCode": "INR",
                          "foreignCurrencyCode": "INR",
                          "foreignAmount": 17750,
                          "ticketCode": null
                        },
                        {
                          "amount": 50,
                          "code": "CUTE",
                          "detail": "SXR-BLR",
                          "type": 4,
                          "collectType": 0,
                          "currencyCode": "INR",
                          "foreignCurrencyCode": "INR",
                          "foreignAmount": 50,
                          "ticketCode": "PHF"
                        },
                        {
                          "amount": 465,
                          "code": "UDF",
                          "detail": "SXR-BLR",
                          "type": 4,
                          "collectType": 0,
                          "currencyCode": "INR",
                          "foreignCurrencyCode": "INR",
                          "foreignAmount": 465,
                          "ticketCode": "UDF"
                        },
                        {
                          "amount": 444,
                          "code": "C01",
                          "detail": "SXR-BLR",
                          "type": 5,
                          "collectType": 0,
                          "currencyCode": "INR",
                          "foreignCurrencyCode": "INR",
                          "foreignAmount": 444,
                          "ticketCode": "C01"
                        },
                        {
                          "amount": 1,
                          "code": "C01",
                          "detail": "SXR-BLR",
                          "type": 5,
                          "collectType": 0,
                          "currencyCode": "INR",
                          "foreignCurrencyCode": "INR",
                          "foreignAmount": 1,
                          "ticketCode": "C01"
                        },
                        {
                          "amount": 444,
                          "code": "S01",
                          "detail": "SXR-BLR",
                          "type": 5,
                          "collectType": 0,
                          "currencyCode": "INR",
                          "foreignCurrencyCode": "INR",
                          "foreignAmount": 444,
                          "ticketCode": "S01"
                        },
                        {
                          "amount": 1,
                          "code": "S01",
                          "detail": "SXR-BLR",
                          "type": 5,
                          "collectType": 0,
                          "currencyCode": "INR",
                          "foreignCurrencyCode": "INR",
                          "foreignAmount": 1,
                          "ticketCode": "S01"
                        }
                      ],
                      "discountCode": null,
                      "fareDiscountCode": null,
                      "passengerType": "ADT"
                    },
                    {
                      "serviceCharges": [
                        {
                          "amount": 17750,
                          "code": null,
                          "detail": null,
                          "type": 0,
                          "collectType": 0,
                          "currencyCode": "INR",
                          "foreignCurrencyCode": "INR",
                          "foreignAmount": 17750,
                          "ticketCode": null
                        },
                        {
                          "amount": 50,
                          "code": "CUTE",
                          "detail": "SXR-BLR",
                          "type": 4,
                          "collectType": 0,
                          "currencyCode": "INR",
                          "foreignCurrencyCode": "INR",
                          "foreignAmount": 50,
                          "ticketCode": "PHF"
                        },
                        {
                          "amount": 465,
                          "code": "UDF",
                          "detail": "SXR-BLR",
                          "type": 4,
                          "collectType": 0,
                          "currencyCode": "INR",
                          "foreignCurrencyCode": "INR",
                          "foreignAmount": 465,
                          "ticketCode": "UDF"
                        },
                        {
                          "amount": 444,
                          "code": "C01",
                          "detail": "SXR-BLR",
                          "type": 5,
                          "collectType": 0,
                          "currencyCode": "INR",
                          "foreignCurrencyCode": "INR",
                          "foreignAmount": 444,
                          "ticketCode": "C01"
                        },
                        {
                          "amount": 1,
                          "code": "C01",
                          "detail": "SXR-BLR",
                          "type": 5,
                          "collectType": 0,
                          "currencyCode": "INR",
                          "foreignCurrencyCode": "INR",
                          "foreignAmount": 1,
                          "ticketCode": "C01"
                        },
                        {
                          "amount": 444,
                          "code": "S01",
                          "detail": "SXR-BLR",
                          "type": 5,
                          "collectType": 0,
                          "currencyCode": "INR",
                          "foreignCurrencyCode": "INR",
                          "foreignAmount": 444,
                          "ticketCode": "S01"
                        },
                        {
                          "amount": 1,
                          "code": "S01",
                          "detail": "SXR-BLR",
                          "type": 5,
                          "collectType": 0,
                          "currencyCode": "INR",
                          "foreignCurrencyCode": "INR",
                          "foreignAmount": 1,
                          "ticketCode": "S01"
                        }
                      ],
                      "discountCode": null,
                      "fareDiscountCode": null,
                      "passengerType": "CHD"
                    }
                  ],
                  "fareLink": 2
                }
              ],
              "segmentKey": "UVB_IDYwMn4gfn5TWFJ_MTAvMTQvMjAyMiAxMDowMH5CTFJ_MTAvMTQvMjAyMiAxMzo1MH5ERUx _",
              "identifier": {
                "identifier": "602",
                "carrierCode": "QP",
                "opSuffix": null
              },
              "passengerSegment": {
                "MCFBRFQ-": {
                  "seats": [],
                  "passengerKey": "MCFBRFQ-",
                  "activityDate": null,
                  "boardingSequence": null,
                  "createdDate": null,
                  "liftStatus": 0,
                  "modifiedDate": null,
                  "overBookIndicator": 0,
                  "priorityDate": null,
                  "timeChanged": false,
                  "verifiedTravelDocs": null,
                  "sourcePointOfSale": null,
                  "pointOfSale": null,
                  "ssrs": [],
                  "tickets": [],
                  "bags": [],
                  "scores": [],
                  "boardingPassDetail": null,
                  "hasInfant": false,
                  "seatPreferences": {
                    "seat": 0,
                    "travelClass": 0,
                    "advancedPreferences": []
                  },
                  "bundleCode": null,
                  "verifiedTravelDocuments": null,
                  "referenceNumber": 0,
                  "baggageGroupNumber": null
                },
                "MSFBRFQ-": {
                  "seats": [],
                  "passengerKey": "MSFBRFQ-",
                  "activityDate": null,
                  "boardingSequence": null,
                  "createdDate": null,
                  "liftStatus": 0,
                  "modifiedDate": null,
                  "overBookIndicator": 0,
                  "priorityDate": null,
                  "timeChanged": false,
                  "verifiedTravelDocs": null,
                  "sourcePointOfSale": null,
                  "pointOfSale": null,
                  "ssrs": [],
                  "tickets": [],
                  "bags": [],
                  "scores": [],
                  "boardingPassDetail": null,
                  "hasInfant": false,
                  "seatPreferences": {
                    "seat": 0,
                    "travelClass": 0,
                    "advancedPreferences": []
                  },
                  "bundleCode": null,
                  "verifiedTravelDocuments": null,
                  "referenceNumber": 0,
                  "baggageGroupNumber": null
                },
                "MiFDSEQ-": {
                  "seats": [],
                  "passengerKey": "MiFDSEQ-",
                  "activityDate": null,
                  "boardingSequence": null,
                  "createdDate": null,
                  "liftStatus": 0,
                  "modifiedDate": null,
                  "overBookIndicator": 0,
                  "priorityDate": null,
                  "timeChanged": false,
                  "verifiedTravelDocs": null,
                  "sourcePointOfSale": null,
                  "pointOfSale": null,
                  "ssrs": [],
                  "tickets": [],
                  "bags": [],
                  "scores": [],
                  "boardingPassDetail": null,
                  "hasInfant": false,
                  "seatPreferences": {
                    "seat": 0,
                    "travelClass": 0,
                    "advancedPreferences": []
                  },
                  "bundleCode": null,
                  "verifiedTravelDocuments": null,
                  "referenceNumber": 0,
                  "baggageGroupNumber": null
                }
              },
              "channelType": 5,
              "cabinOfService": "Y",
              "externalIdentifier": null,
              "priorityCode": null,
              "changeReasonCode": 0,
              "segmentType": 0,
              "salesDate": null,
              "international": false,
              "flightReference": "20221014 QP 602 SXRBLR",
              "legs": [
                {
                  "legKey": "NjM4MDEzMzg0MDAwMDAwMDAwIVFQITYwMiEgIVNYUiFERUwhMzQ0MTg-",
                  "operationsInfo": null,
                  "designator": {
                    "destination": "DEL",
                    "origin": "SXR",
                    "arrival": "2022-10-14T11:10:00",
                    "departure": "2022-10-14T10:00:00"
                  },
                  "legInfo": {
                    "arrivalTimeUtc": "2022-10-14T05:40:00Z",
                    "departureTimeUtc": "2022-10-14T04:30:00Z",
                    "adjustedCapacity": 189,
                    "arrivalTerminal": "T2",
                    "arrivalTimeVariant": 330,
                    "backMoveDays": 365,
                    "capacity": 189,
                    "changeOfDirection": false,
                    "codeShareIndicator": 0,
                    "departureTerminal": null,
                    "departureTimeVariant": 330,
                    "equipmentType": "999",
                    "equipmentTypeSuffix": "YA",
                    "eTicket": true,
                    "irop": false,
                    "lid": 189,
                    "marketingCode": null,
                    "marketingOverride": false,
                    "operatedByText": null,
                    "operatingCarrier": null,
                    "operatingFlightNumber": null,
                    "operatingOpSuffix": null,
                    "outMoveDays": 365,
                    "arrivalTime": "2022-10-14T11:10:00",
                    "departureTime": "2022-10-14T10:00:00",
                    "prbcCode": "TSTSLS1",
                    "scheduleServiceType": "J",
                    "sold": 0,
                    "status": 0,
                    "subjectToGovtApproval": false
                  },
                  "nests": [
                    {
                      "adjustedCapacity": 189,
                      "classNest": 1,
                      "lid": 189,
                      "travelClassCode": "Y",
                      "nestType": 1,
                      "legClasses": [
                        {
                          "classNest": 1,
                          "classAllotted": 0,
                          "classType": null,
                          "classAuthorizedUnits": 0,
                          "classOfService": "G",
                          "classRank": 21,
                          "classSold": 0,
                          "cnxSold": 0,
                          "latestAdvancedReservation": 0,
                          "status": 1,
                          "thruSold": 0
                        },
                        {
                          "classNest": 1,
                          "classAllotted": 0,
                          "classType": null,
                          "classAuthorizedUnits": 0,
                          "classOfService": "Z",
                          "classRank": 20,
                          "classSold": 0,
                          "cnxSold": 0,
                          "latestAdvancedReservation": 0,
                          "status": 1,
                          "thruSold": 0
                        },
                        {
                          "classNest": 1,
                          "classAllotted": 0,
                          "classType": null,
                          "classAuthorizedUnits": 0,
                          "classOfService": "V",
                          "classRank": 19,
                          "classSold": 0,
                          "cnxSold": 0,
                          "latestAdvancedReservation": 0,
                          "status": 1,
                          "thruSold": 0
                        },
                        {
                          "classNest": 1,
                          "classAllotted": 0,
                          "classType": null,
                          "classAuthorizedUnits": 0,
                          "classOfService": "U",
                          "classRank": 18,
                          "classSold": 0,
                          "cnxSold": 0,
                          "latestAdvancedReservation": 0,
                          "status": 1,
                          "thruSold": 0
                        },
                        {
                          "classNest": 1,
                          "classAllotted": 0,
                          "classType": null,
                          "classAuthorizedUnits": 0,
                          "classOfService": "T",
                          "classRank": 17,
                          "classSold": 0,
                          "cnxSold": 0,
                          "latestAdvancedReservation": 0,
                          "status": 1,
                          "thruSold": 0
                        },
                        {
                          "classNest": 1,
                          "classAllotted": 0,
                          "classType": null,
                          "classAuthorizedUnits": 0,
                          "classOfService": "R",
                          "classRank": 16,
                          "classSold": 0,
                          "cnxSold": 0,
                          "latestAdvancedReservation": 0,
                          "status": 1,
                          "thruSold": 0
                        },
                        {
                          "classNest": 1,
                          "classAllotted": 0,
                          "classType": null,
                          "classAuthorizedUnits": 0,
                          "classOfService": "Q",
                          "classRank": 15,
                          "classSold": 0,
                          "cnxSold": 0,
                          "latestAdvancedReservation": 0,
                          "status": 1,
                          "thruSold": 0
                        },
                        {
                          "classNest": 1,
                          "classAllotted": 0,
                          "classType": null,
                          "classAuthorizedUnits": 0,
                          "classOfService": "O",
                          "classRank": 14,
                          "classSold": 0,
                          "cnxSold": 0,
                          "latestAdvancedReservation": 0,
                          "status": 1,
                          "thruSold": 0
                        },
                        {
                          "classNest": 1,
                          "classAllotted": 0,
                          "classType": null,
                          "classAuthorizedUnits": 0,
                          "classOfService": "N",
                          "classRank": 13,
                          "classSold": 0,
                          "cnxSold": 0,
                          "latestAdvancedReservation": 0,
                          "status": 1,
                          "thruSold": 0
                        },
                        {
                          "classNest": 1,
                          "classAllotted": 0,
                          "classType": null,
                          "classAuthorizedUnits": 0,
                          "classOfService": "M",
                          "classRank": 12,
                          "classSold": 0,
                          "cnxSold": 0,
                          "latestAdvancedReservation": 0,
                          "status": 1,
                          "thruSold": 0
                        },
                        {
                          "classNest": 1,
                          "classAllotted": 0,
                          "classType": null,
                          "classAuthorizedUnits": 0,
                          "classOfService": "L",
                          "classRank": 11,
                          "classSold": 0,
                          "cnxSold": 0,
                          "latestAdvancedReservation": 0,
                          "status": 1,
                          "thruSold": 0
                        },
                        {
                          "classNest": 1,
                          "classAllotted": 0,
                          "classType": null,
                          "classAuthorizedUnits": 0,
                          "classOfService": "K",
                          "classRank": 10,
                          "classSold": 0,
                          "cnxSold": 0,
                          "latestAdvancedReservation": 0,
                          "status": 1,
                          "thruSold": 0
                        },
                        {
                          "classNest": 1,
                          "classAllotted": 0,
                          "classType": null,
                          "classAuthorizedUnits": 0,
                          "classOfService": "J",
                          "classRank": 9,
                          "classSold": 0,
                          "cnxSold": 0,
                          "latestAdvancedReservation": 0,
                          "status": 1,
                          "thruSold": 0
                        },
                        {
                          "classNest": 1,
                          "classAllotted": 0,
                          "classType": null,
                          "classAuthorizedUnits": 0,
                          "classOfService": "I",
                          "classRank": 8,
                          "classSold": 0,
                          "cnxSold": 0,
                          "latestAdvancedReservation": 0,
                          "status": 1,
                          "thruSold": 0
                        },
                        {
                          "classNest": 1,
                          "classAllotted": 0,
                          "classType": null,
                          "classAuthorizedUnits": 0,
                          "classOfService": "H",
                          "classRank": 7,
                          "classSold": 0,
                          "cnxSold": 0,
                          "latestAdvancedReservation": 0,
                          "status": 1,
                          "thruSold": 0
                        },
                        {
                          "classNest": 1,
                          "classAllotted": 0,
                          "classType": null,
                          "classAuthorizedUnits": 0,
                          "classOfService": "F",
                          "classRank": 6,
                          "classSold": 0,
                          "cnxSold": 0,
                          "latestAdvancedReservation": 0,
                          "status": 1,
                          "thruSold": 0
                        },
                        {
                          "classNest": 1,
                          "classAllotted": 0,
                          "classType": null,
                          "classAuthorizedUnits": 0,
                          "classOfService": "E",
                          "classRank": 5,
                          "classSold": 0,
                          "cnxSold": 0,
                          "latestAdvancedReservation": 0,
                          "status": 1,
                          "thruSold": 0
                        },
                        {
                          "classNest": 1,
                          "classAllotted": 0,
                          "classType": null,
                          "classAuthorizedUnits": 0,
                          "classOfService": "D",
                          "classRank": 4,
                          "classSold": 0,
                          "cnxSold": 0,
                          "latestAdvancedReservation": 0,
                          "status": 1,
                          "thruSold": 0
                        },
                        {
                          "classNest": 1,
                          "classAllotted": 0,
                          "classType": null,
                          "classAuthorizedUnits": 0,
                          "classOfService": "C",
                          "classRank": 3,
                          "classSold": 0,
                          "cnxSold": 0,
                          "latestAdvancedReservation": 0,
                          "status": 1,
                          "thruSold": 0
                        },
                        {
                          "classNest": 1,
                          "classAllotted": 0,
                          "classType": null,
                          "classAuthorizedUnits": 30,
                          "classOfService": "B",
                          "classRank": 2,
                          "classSold": 0,
                          "cnxSold": 0,
                          "latestAdvancedReservation": 0,
                          "status": 1,
                          "thruSold": 0
                        },
                        {
                          "classNest": 1,
                          "classAllotted": 0,
                          "classType": null,
                          "classAuthorizedUnits": 180,
                          "classOfService": "Y",
                          "classRank": 1,
                          "classSold": 0,
                          "cnxSold": 0,
                          "latestAdvancedReservation": 0,
                          "status": 1,
                          "thruSold": 0
                        },
                        {
                          "classNest": 1,
                          "classAllotted": 0,
                          "classType": null,
                          "classAuthorizedUnits": 0,
                          "classOfService": "Z6",
                          "classRank": 37,
                          "classSold": 0,
                          "cnxSold": 0,
                          "latestAdvancedReservation": 0,
                          "status": 2,
                          "thruSold": 0
                        },
                        {
                          "classNest": 1,
                          "classAllotted": 0,
                          "classType": null,
                          "classAuthorizedUnits": 0,
                          "classOfService": "Z5",
                          "classRank": 36,
                          "classSold": 0,
                          "cnxSold": 0,
                          "latestAdvancedReservation": 0,
                          "status": 2,
                          "thruSold": 0
                        },
                        {
                          "classNest": 1,
                          "classAllotted": 0,
                          "classType": null,
                          "classAuthorizedUnits": 0,
                          "classOfService": "Z4",
                          "classRank": 35,
                          "classSold": 0,
                          "cnxSold": 0,
                          "latestAdvancedReservation": 0,
                          "status": 2,
                          "thruSold": 0
                        },
                        {
                          "classNest": 1,
                          "classAllotted": 0,
                          "classType": null,
                          "classAuthorizedUnits": 0,
                          "classOfService": "Z3",
                          "classRank": 34,
                          "classSold": 0,
                          "cnxSold": 0,
                          "latestAdvancedReservation": 0,
                          "status": 2,
                          "thruSold": 0
                        },
                        {
                          "classNest": 1,
                          "classAllotted": 0,
                          "classType": null,
                          "classAuthorizedUnits": 0,
                          "classOfService": "Z2",
                          "classRank": 33,
                          "classSold": 0,
                          "cnxSold": 0,
                          "latestAdvancedReservation": 0,
                          "status": 2,
                          "thruSold": 0
                        },
                        {
                          "classNest": 1,
                          "classAllotted": 0,
                          "classType": null,
                          "classAuthorizedUnits": 0,
                          "classOfService": "Z1",
                          "classRank": 32,
                          "classSold": 0,
                          "cnxSold": 0,
                          "latestAdvancedReservation": 0,
                          "status": 2,
                          "thruSold": 0
                        },
                        {
                          "classNest": 1,
                          "classAllotted": 0,
                          "classType": null,
                          "classAuthorizedUnits": 0,
                          "classOfService": "Z0",
                          "classRank": 31,
                          "classSold": 0,
                          "cnxSold": 0,
                          "latestAdvancedReservation": 0,
                          "status": 2,
                          "thruSold": 0
                        },
                        {
                          "classNest": 1,
                          "classAllotted": 0,
                          "classType": null,
                          "classAuthorizedUnits": 0,
                          "classOfService": "V6",
                          "classRank": 30,
                          "classSold": 0,
                          "cnxSold": 0,
                          "latestAdvancedReservation": 0,
                          "status": 2,
                          "thruSold": 0
                        },
                        {
                          "classNest": 1,
                          "classAllotted": 0,
                          "classType": null,
                          "classAuthorizedUnits": 0,
                          "classOfService": "V5",
                          "classRank": 29,
                          "classSold": 0,
                          "cnxSold": 0,
                          "latestAdvancedReservation": 0,
                          "status": 2,
                          "thruSold": 0
                        },
                        {
                          "classNest": 1,
                          "classAllotted": 0,
                          "classType": null,
                          "classAuthorizedUnits": 0,
                          "classOfService": "V4",
                          "classRank": 28,
                          "classSold": 0,
                          "cnxSold": 0,
                          "latestAdvancedReservation": 0,
                          "status": 2,
                          "thruSold": 0
                        },
                        {
                          "classNest": 1,
                          "classAllotted": 0,
                          "classType": null,
                          "classAuthorizedUnits": 0,
                          "classOfService": "V3",
                          "classRank": 27,
                          "classSold": 0,
                          "cnxSold": 0,
                          "latestAdvancedReservation": 0,
                          "status": 2,
                          "thruSold": 0
                        },
                        {
                          "classNest": 1,
                          "classAllotted": 0,
                          "classType": null,
                          "classAuthorizedUnits": 0,
                          "classOfService": "V2",
                          "classRank": 26,
                          "classSold": 0,
                          "cnxSold": 0,
                          "latestAdvancedReservation": 0,
                          "status": 2,
                          "thruSold": 0
                        },
                        {
                          "classNest": 1,
                          "classAllotted": 0,
                          "classType": "X",
                          "classAuthorizedUnits": 0,
                          "classOfService": "A",
                          "classRank": 26,
                          "classSold": 0,
                          "cnxSold": 0,
                          "latestAdvancedReservation": 0,
                          "status": 1,
                          "thruSold": 0
                        },
                        {
                          "classNest": 1,
                          "classAllotted": 0,
                          "classType": null,
                          "classAuthorizedUnits": 0,
                          "classOfService": "V1",
                          "classRank": 25,
                          "classSold": 0,
                          "cnxSold": 0,
                          "latestAdvancedReservation": 0,
                          "status": 2,
                          "thruSold": 0
                        },
                        {
                          "classNest": 1,
                          "classAllotted": 0,
                          "classType": "X",
                          "classAuthorizedUnits": 0,
                          "classOfService": "X",
                          "classRank": 25,
                          "classSold": 0,
                          "cnxSold": 0,
                          "latestAdvancedReservation": 0,
                          "status": 1,
                          "thruSold": 0
                        },
                        {
                          "classNest": 1,
                          "classAllotted": 0,
                          "classType": "X",
                          "classAuthorizedUnits": 0,
                          "classOfService": "W",
                          "classRank": 24,
                          "classSold": 0,
                          "cnxSold": 0,
                          "latestAdvancedReservation": 0,
                          "status": 1,
                          "thruSold": 0
                        },
                        {
                          "classNest": 1,
                          "classAllotted": 0,
                          "classType": null,
                          "classAuthorizedUnits": 0,
                          "classOfService": "V0",
                          "classRank": 24,
                          "classSold": 0,
                          "cnxSold": 0,
                          "latestAdvancedReservation": 0,
                          "status": 2,
                          "thruSold": 0
                        },
                        {
                          "classNest": 1,
                          "classAllotted": 0,
                          "classType": null,
                          "classAuthorizedUnits": 0,
                          "classOfService": "U6",
                          "classRank": 23,
                          "classSold": 0,
                          "cnxSold": 0,
                          "latestAdvancedReservation": 0,
                          "status": 2,
                          "thruSold": 0
                        },
                        {
                          "classNest": 1,
                          "classAllotted": 0,
                          "classType": "T",
                          "classAuthorizedUnits": 0,
                          "classOfService": "S",
                          "classRank": 23,
                          "classSold": 0,
                          "cnxSold": 0,
                          "latestAdvancedReservation": 0,
                          "status": 1,
                          "thruSold": 0
                        },
                        {
                          "classNest": 1,
                          "classAllotted": 0,
                          "classType": null,
                          "classAuthorizedUnits": 0,
                          "classOfService": "U5",
                          "classRank": 22,
                          "classSold": 0,
                          "cnxSold": 0,
                          "latestAdvancedReservation": 0,
                          "status": 2,
                          "thruSold": 0
                        },
                        {
                          "classNest": 1,
                          "classAllotted": 0,
                          "classType": "T",
                          "classAuthorizedUnits": 0,
                          "classOfService": "P",
                          "classRank": 22,
                          "classSold": 0,
                          "cnxSold": 0,
                          "latestAdvancedReservation": 0,
                          "status": 1,
                          "thruSold": 0
                        },
                        {
                          "classNest": 1,
                          "classAllotted": 0,
                          "classType": null,
                          "classAuthorizedUnits": 0,
                          "classOfService": "U4",
                          "classRank": 21,
                          "classSold": 0,
                          "cnxSold": 0,
                          "latestAdvancedReservation": 0,
                          "status": 2,
                          "thruSold": 0
                        },
                        {
                          "classNest": 1,
                          "classAllotted": 0,
                          "classType": null,
                          "classAuthorizedUnits": 0,
                          "classOfService": "U3",
                          "classRank": 20,
                          "classSold": 0,
                          "cnxSold": 0,
                          "latestAdvancedReservation": 0,
                          "status": 2,
                          "thruSold": 0
                        },
                        {
                          "classNest": 1,
                          "classAllotted": 0,
                          "classType": null,
                          "classAuthorizedUnits": 0,
                          "classOfService": "U2",
                          "classRank": 19,
                          "classSold": 0,
                          "cnxSold": 0,
                          "latestAdvancedReservation": 0,
                          "status": 2,
                          "thruSold": 0
                        },
                        {
                          "classNest": 1,
                          "classAllotted": 0,
                          "classType": null,
                          "classAuthorizedUnits": 0,
                          "classOfService": "U1",
                          "classRank": 18,
                          "classSold": 0,
                          "cnxSold": 0,
                          "latestAdvancedReservation": 0,
                          "status": 2,
                          "thruSold": 0
                        },
                        {
                          "classNest": 1,
                          "classAllotted": 0,
                          "classType": null,
                          "classAuthorizedUnits": 0,
                          "classOfService": "U0",
                          "classRank": 17,
                          "classSold": 0,
                          "cnxSold": 0,
                          "latestAdvancedReservation": 0,
                          "status": 2,
                          "thruSold": 0
                        }
                      ]
                    }
                  ],
                  "ssrs": [
                    {
                      "available": 10,
                      "ssrNestCode": "INFT",
                      "lid": 10,
                      "sold": 0,
                      "unitSold": 0
                    }
                  ],
                  "seatmapReference": "UVAhIDYwMiEgITYzODAxMzM4NDAwMDAwMDAwMCFTWFIhQkxS",
                  "flightReference": "20221014 QP 602 SXRDEL"
                },
                {
                  "legKey": "NjM4MDEzNDU2MDAwMDAwMDAwIVFQITYwMiEgIURFTCFCTFIhMzQ0MTc-",
                  "operationsInfo": null,
                  "designator": {
                    "destination": "BLR",
                    "origin": "DEL",
                    "arrival": "2022-10-14T13:50:00",
                    "departure": "2022-10-14T12:00:00"
                  },
                  "legInfo": {
                    "arrivalTimeUtc": "2022-10-14T08:20:00Z",
                    "departureTimeUtc": "2022-10-14T06:30:00Z",
                    "adjustedCapacity": 189,
                    "arrivalTerminal": "T1",
                    "arrivalTimeVariant": 330,
                    "backMoveDays": 365,
                    "capacity": 189,
                    "changeOfDirection": false,
                    "codeShareIndicator": 0,
                    "departureTerminal": "T2",
                    "departureTimeVariant": 330,
                    "equipmentType": "999",
                    "equipmentTypeSuffix": "YA",
                    "eTicket": true,
                    "irop": false,
                    "lid": 189,
                    "marketingCode": null,
                    "marketingOverride": false,
                    "operatedByText": null,
                    "operatingCarrier": null,
                    "operatingFlightNumber": null,
                    "operatingOpSuffix": null,
                    "outMoveDays": 365,
                    "arrivalTime": "2022-10-14T13:50:00",
                    "departureTime": "2022-10-14T12:00:00",
                    "prbcCode": "TSTSLS1",
                    "scheduleServiceType": "J",
                    "sold": 0,
                    "status": 0,
                    "subjectToGovtApproval": false
                  },
                  "nests": [
                    {
                      "adjustedCapacity": 189,
                      "classNest": 1,
                      "lid": 189,
                      "travelClassCode": "Y",
                      "nestType": 1,
                      "legClasses": [
                        {
                          "classNest": 1,
                          "classAllotted": 0,
                          "classType": null,
                          "classAuthorizedUnits": 0,
                          "classOfService": "G",
                          "classRank": 21,
                          "classSold": 0,
                          "cnxSold": 0,
                          "latestAdvancedReservation": 0,
                          "status": 1,
                          "thruSold": 0
                        },
                        {
                          "classNest": 1,
                          "classAllotted": 0,
                          "classType": null,
                          "classAuthorizedUnits": 0,
                          "classOfService": "Z",
                          "classRank": 20,
                          "classSold": 0,
                          "cnxSold": 0,
                          "latestAdvancedReservation": 0,
                          "status": 1,
                          "thruSold": 0
                        },
                        {
                          "classNest": 1,
                          "classAllotted": 0,
                          "classType": null,
                          "classAuthorizedUnits": 0,
                          "classOfService": "V",
                          "classRank": 19,
                          "classSold": 0,
                          "cnxSold": 0,
                          "latestAdvancedReservation": 0,
                          "status": 1,
                          "thruSold": 0
                        },
                        {
                          "classNest": 1,
                          "classAllotted": 0,
                          "classType": null,
                          "classAuthorizedUnits": 0,
                          "classOfService": "U",
                          "classRank": 18,
                          "classSold": 0,
                          "cnxSold": 0,
                          "latestAdvancedReservation": 0,
                          "status": 1,
                          "thruSold": 0
                        },
                        {
                          "classNest": 1,
                          "classAllotted": 0,
                          "classType": null,
                          "classAuthorizedUnits": 0,
                          "classOfService": "T",
                          "classRank": 17,
                          "classSold": 0,
                          "cnxSold": 0,
                          "latestAdvancedReservation": 0,
                          "status": 1,
                          "thruSold": 0
                        },
                        {
                          "classNest": 1,
                          "classAllotted": 0,
                          "classType": null,
                          "classAuthorizedUnits": 0,
                          "classOfService": "R",
                          "classRank": 16,
                          "classSold": 0,
                          "cnxSold": 0,
                          "latestAdvancedReservation": 0,
                          "status": 1,
                          "thruSold": 0
                        },
                        {
                          "classNest": 1,
                          "classAllotted": 0,
                          "classType": null,
                          "classAuthorizedUnits": 0,
                          "classOfService": "Q",
                          "classRank": 15,
                          "classSold": 0,
                          "cnxSold": 0,
                          "latestAdvancedReservation": 0,
                          "status": 1,
                          "thruSold": 0
                        },
                        {
                          "classNest": 1,
                          "classAllotted": 0,
                          "classType": null,
                          "classAuthorizedUnits": 0,
                          "classOfService": "O",
                          "classRank": 14,
                          "classSold": 0,
                          "cnxSold": 0,
                          "latestAdvancedReservation": 0,
                          "status": 1,
                          "thruSold": 0
                        },
                        {
                          "classNest": 1,
                          "classAllotted": 0,
                          "classType": null,
                          "classAuthorizedUnits": 0,
                          "classOfService": "N",
                          "classRank": 13,
                          "classSold": 0,
                          "cnxSold": 0,
                          "latestAdvancedReservation": 0,
                          "status": 1,
                          "thruSold": 0
                        },
                        {
                          "classNest": 1,
                          "classAllotted": 0,
                          "classType": null,
                          "classAuthorizedUnits": 0,
                          "classOfService": "M",
                          "classRank": 12,
                          "classSold": 0,
                          "cnxSold": 0,
                          "latestAdvancedReservation": 0,
                          "status": 1,
                          "thruSold": 0
                        },
                        {
                          "classNest": 1,
                          "classAllotted": 0,
                          "classType": null,
                          "classAuthorizedUnits": 0,
                          "classOfService": "L",
                          "classRank": 11,
                          "classSold": 0,
                          "cnxSold": 0,
                          "latestAdvancedReservation": 0,
                          "status": 1,
                          "thruSold": 0
                        },
                        {
                          "classNest": 1,
                          "classAllotted": 0,
                          "classType": null,
                          "classAuthorizedUnits": 0,
                          "classOfService": "K",
                          "classRank": 10,
                          "classSold": 0,
                          "cnxSold": 0,
                          "latestAdvancedReservation": 0,
                          "status": 1,
                          "thruSold": 0
                        },
                        {
                          "classNest": 1,
                          "classAllotted": 0,
                          "classType": null,
                          "classAuthorizedUnits": 0,
                          "classOfService": "J",
                          "classRank": 9,
                          "classSold": 0,
                          "cnxSold": 0,
                          "latestAdvancedReservation": 0,
                          "status": 1,
                          "thruSold": 0
                        },
                        {
                          "classNest": 1,
                          "classAllotted": 0,
                          "classType": null,
                          "classAuthorizedUnits": 0,
                          "classOfService": "I",
                          "classRank": 8,
                          "classSold": 0,
                          "cnxSold": 0,
                          "latestAdvancedReservation": 0,
                          "status": 1,
                          "thruSold": 0
                        },
                        {
                          "classNest": 1,
                          "classAllotted": 0,
                          "classType": null,
                          "classAuthorizedUnits": 0,
                          "classOfService": "H",
                          "classRank": 7,
                          "classSold": 0,
                          "cnxSold": 0,
                          "latestAdvancedReservation": 0,
                          "status": 1,
                          "thruSold": 0
                        },
                        {
                          "classNest": 1,
                          "classAllotted": 0,
                          "classType": null,
                          "classAuthorizedUnits": 0,
                          "classOfService": "F",
                          "classRank": 6,
                          "classSold": 0,
                          "cnxSold": 0,
                          "latestAdvancedReservation": 0,
                          "status": 1,
                          "thruSold": 0
                        },
                        {
                          "classNest": 1,
                          "classAllotted": 0,
                          "classType": null,
                          "classAuthorizedUnits": 0,
                          "classOfService": "E",
                          "classRank": 5,
                          "classSold": 0,
                          "cnxSold": 0,
                          "latestAdvancedReservation": 0,
                          "status": 1,
                          "thruSold": 0
                        },
                        {
                          "classNest": 1,
                          "classAllotted": 0,
                          "classType": null,
                          "classAuthorizedUnits": 0,
                          "classOfService": "D",
                          "classRank": 4,
                          "classSold": 0,
                          "cnxSold": 0,
                          "latestAdvancedReservation": 0,
                          "status": 1,
                          "thruSold": 0
                        },
                        {
                          "classNest": 1,
                          "classAllotted": 0,
                          "classType": null,
                          "classAuthorizedUnits": 0,
                          "classOfService": "C",
                          "classRank": 3,
                          "classSold": 0,
                          "cnxSold": 0,
                          "latestAdvancedReservation": 0,
                          "status": 1,
                          "thruSold": 0
                        },
                        {
                          "classNest": 1,
                          "classAllotted": 0,
                          "classType": null,
                          "classAuthorizedUnits": 30,
                          "classOfService": "B",
                          "classRank": 2,
                          "classSold": 0,
                          "cnxSold": 0,
                          "latestAdvancedReservation": 0,
                          "status": 1,
                          "thruSold": 0
                        },
                        {
                          "classNest": 1,
                          "classAllotted": 0,
                          "classType": null,
                          "classAuthorizedUnits": 180,
                          "classOfService": "Y",
                          "classRank": 1,
                          "classSold": 0,
                          "cnxSold": 0,
                          "latestAdvancedReservation": 0,
                          "status": 1,
                          "thruSold": 0
                        },
                        {
                          "classNest": 1,
                          "classAllotted": 0,
                          "classType": null,
                          "classAuthorizedUnits": 0,
                          "classOfService": "Z6",
                          "classRank": 37,
                          "classSold": 0,
                          "cnxSold": 0,
                          "latestAdvancedReservation": 0,
                          "status": 2,
                          "thruSold": 0
                        },
                        {
                          "classNest": 1,
                          "classAllotted": 0,
                          "classType": null,
                          "classAuthorizedUnits": 0,
                          "classOfService": "Z5",
                          "classRank": 36,
                          "classSold": 0,
                          "cnxSold": 0,
                          "latestAdvancedReservation": 0,
                          "status": 2,
                          "thruSold": 0
                        },
                        {
                          "classNest": 1,
                          "classAllotted": 0,
                          "classType": null,
                          "classAuthorizedUnits": 0,
                          "classOfService": "Z4",
                          "classRank": 35,
                          "classSold": 0,
                          "cnxSold": 0,
                          "latestAdvancedReservation": 0,
                          "status": 2,
                          "thruSold": 0
                        },
                        {
                          "classNest": 1,
                          "classAllotted": 0,
                          "classType": null,
                          "classAuthorizedUnits": 0,
                          "classOfService": "Z3",
                          "classRank": 34,
                          "classSold": 0,
                          "cnxSold": 0,
                          "latestAdvancedReservation": 0,
                          "status": 2,
                          "thruSold": 0
                        },
                        {
                          "classNest": 1,
                          "classAllotted": 0,
                          "classType": null,
                          "classAuthorizedUnits": 0,
                          "classOfService": "Z2",
                          "classRank": 33,
                          "classSold": 0,
                          "cnxSold": 0,
                          "latestAdvancedReservation": 0,
                          "status": 2,
                          "thruSold": 0
                        },
                        {
                          "classNest": 1,
                          "classAllotted": 0,
                          "classType": null,
                          "classAuthorizedUnits": 0,
                          "classOfService": "Z1",
                          "classRank": 32,
                          "classSold": 0,
                          "cnxSold": 0,
                          "latestAdvancedReservation": 0,
                          "status": 2,
                          "thruSold": 0
                        },
                        {
                          "classNest": 1,
                          "classAllotted": 0,
                          "classType": null,
                          "classAuthorizedUnits": 0,
                          "classOfService": "Z0",
                          "classRank": 31,
                          "classSold": 0,
                          "cnxSold": 0,
                          "latestAdvancedReservation": 0,
                          "status": 2,
                          "thruSold": 0
                        },
                        {
                          "classNest": 1,
                          "classAllotted": 0,
                          "classType": null,
                          "classAuthorizedUnits": 0,
                          "classOfService": "V6",
                          "classRank": 30,
                          "classSold": 0,
                          "cnxSold": 0,
                          "latestAdvancedReservation": 0,
                          "status": 2,
                          "thruSold": 0
                        },
                        {
                          "classNest": 1,
                          "classAllotted": 0,
                          "classType": null,
                          "classAuthorizedUnits": 0,
                          "classOfService": "V5",
                          "classRank": 29,
                          "classSold": 0,
                          "cnxSold": 0,
                          "latestAdvancedReservation": 0,
                          "status": 2,
                          "thruSold": 0
                        },
                        {
                          "classNest": 1,
                          "classAllotted": 0,
                          "classType": null,
                          "classAuthorizedUnits": 0,
                          "classOfService": "V4",
                          "classRank": 28,
                          "classSold": 0,
                          "cnxSold": 0,
                          "latestAdvancedReservation": 0,
                          "status": 2,
                          "thruSold": 0
                        },
                        {
                          "classNest": 1,
                          "classAllotted": 0,
                          "classType": null,
                          "classAuthorizedUnits": 0,
                          "classOfService": "V3",
                          "classRank": 27,
                          "classSold": 0,
                          "cnxSold": 0,
                          "latestAdvancedReservation": 0,
                          "status": 2,
                          "thruSold": 0
                        },
                        {
                          "classNest": 1,
                          "classAllotted": 0,
                          "classType": "X",
                          "classAuthorizedUnits": 0,
                          "classOfService": "A",
                          "classRank": 26,
                          "classSold": 0,
                          "cnxSold": 0,
                          "latestAdvancedReservation": 0,
                          "status": 1,
                          "thruSold": 0
                        },
                        {
                          "classNest": 1,
                          "classAllotted": 0,
                          "classType": null,
                          "classAuthorizedUnits": 0,
                          "classOfService": "V2",
                          "classRank": 26,
                          "classSold": 0,
                          "cnxSold": 0,
                          "latestAdvancedReservation": 0,
                          "status": 2,
                          "thruSold": 0
                        },
                        {
                          "classNest": 1,
                          "classAllotted": 0,
                          "classType": null,
                          "classAuthorizedUnits": 0,
                          "classOfService": "V1",
                          "classRank": 25,
                          "classSold": 0,
                          "cnxSold": 0,
                          "latestAdvancedReservation": 0,
                          "status": 2,
                          "thruSold": 0
                        },
                        {
                          "classNest": 1,
                          "classAllotted": 0,
                          "classType": "X",
                          "classAuthorizedUnits": 0,
                          "classOfService": "X",
                          "classRank": 25,
                          "classSold": 0,
                          "cnxSold": 0,
                          "latestAdvancedReservation": 0,
                          "status": 1,
                          "thruSold": 0
                        },
                        {
                          "classNest": 1,
                          "classAllotted": 0,
                          "classType": "X",
                          "classAuthorizedUnits": 0,
                          "classOfService": "W",
                          "classRank": 24,
                          "classSold": 0,
                          "cnxSold": 0,
                          "latestAdvancedReservation": 0,
                          "status": 1,
                          "thruSold": 0
                        },
                        {
                          "classNest": 1,
                          "classAllotted": 0,
                          "classType": null,
                          "classAuthorizedUnits": 0,
                          "classOfService": "V0",
                          "classRank": 24,
                          "classSold": 0,
                          "cnxSold": 0,
                          "latestAdvancedReservation": 0,
                          "status": 2,
                          "thruSold": 0
                        },
                        {
                          "classNest": 1,
                          "classAllotted": 0,
                          "classType": null,
                          "classAuthorizedUnits": 0,
                          "classOfService": "U6",
                          "classRank": 23,
                          "classSold": 0,
                          "cnxSold": 0,
                          "latestAdvancedReservation": 0,
                          "status": 2,
                          "thruSold": 0
                        },
                        {
                          "classNest": 1,
                          "classAllotted": 0,
                          "classType": "T",
                          "classAuthorizedUnits": 0,
                          "classOfService": "S",
                          "classRank": 23,
                          "classSold": 0,
                          "cnxSold": 0,
                          "latestAdvancedReservation": 0,
                          "status": 1,
                          "thruSold": 0
                        },
                        {
                          "classNest": 1,
                          "classAllotted": 0,
                          "classType": null,
                          "classAuthorizedUnits": 0,
                          "classOfService": "U5",
                          "classRank": 22,
                          "classSold": 0,
                          "cnxSold": 0,
                          "latestAdvancedReservation": 0,
                          "status": 2,
                          "thruSold": 0
                        },
                        {
                          "classNest": 1,
                          "classAllotted": 0,
                          "classType": "T",
                          "classAuthorizedUnits": 0,
                          "classOfService": "P",
                          "classRank": 22,
                          "classSold": 0,
                          "cnxSold": 0,
                          "latestAdvancedReservation": 0,
                          "status": 1,
                          "thruSold": 0
                        },
                        {
                          "classNest": 1,
                          "classAllotted": 0,
                          "classType": null,
                          "classAuthorizedUnits": 0,
                          "classOfService": "U4",
                          "classRank": 21,
                          "classSold": 0,
                          "cnxSold": 0,
                          "latestAdvancedReservation": 0,
                          "status": 2,
                          "thruSold": 0
                        },
                        {
                          "classNest": 1,
                          "classAllotted": 0,
                          "classType": null,
                          "classAuthorizedUnits": 0,
                          "classOfService": "U3",
                          "classRank": 20,
                          "classSold": 0,
                          "cnxSold": 0,
                          "latestAdvancedReservation": 0,
                          "status": 2,
                          "thruSold": 0
                        },
                        {
                          "classNest": 1,
                          "classAllotted": 0,
                          "classType": null,
                          "classAuthorizedUnits": 0,
                          "classOfService": "U2",
                          "classRank": 19,
                          "classSold": 0,
                          "cnxSold": 0,
                          "latestAdvancedReservation": 0,
                          "status": 2,
                          "thruSold": 0
                        },
                        {
                          "classNest": 1,
                          "classAllotted": 0,
                          "classType": null,
                          "classAuthorizedUnits": 0,
                          "classOfService": "U1",
                          "classRank": 18,
                          "classSold": 0,
                          "cnxSold": 0,
                          "latestAdvancedReservation": 0,
                          "status": 2,
                          "thruSold": 0
                        },
                        {
                          "classNest": 1,
                          "classAllotted": 0,
                          "classType": null,
                          "classAuthorizedUnits": 0,
                          "classOfService": "U0",
                          "classRank": 17,
                          "classSold": 0,
                          "cnxSold": 0,
                          "latestAdvancedReservation": 0,
                          "status": 2,
                          "thruSold": 0
                        }
                      ]
                    }
                  ],
                  "ssrs": [
                    {
                      "available": 10,
                      "ssrNestCode": "INFT",
                      "lid": 10,
                      "sold": 0,
                      "unitSold": 0
                    }
                  ],
                  "seatmapReference": "UVAhIDYwMiEgITYzODAxMzM4NDAwMDAwMDAwMCFTWFIhQkxS",
                  "flightReference": "20221014 QP 602 DELBLR"
                }
              ],
              "status": 0
            }
          ],
          "journeyKey": "UVB_IDYwMn4gfn5TWFJ_MTAvMTQvMjAyMiAxMDowMH5CTFJ_MTAvMTQvMjAyMiAxMzo1MH5ERUx _",
          "notForGeneralUser": false
        }
      ],
      "comments": [],
      "queues": [],
      "history": [],
      "payments": [],
      "addOns": {},
      "orders": []
    }
  }